{
  "sku": "50874",
  "title": "Moringa Oleifera",
  "slug": "moringa-oleifera",
  "descriptionHtml": "",
  "shortDescriptionHtml": "",
  "suggestedUse": null,
  "supplementFacts": "Supplement Facts\nServing Size: 2 Veggie Capsules\nServings Per Container: 30\n\nAmount Per Serving / %DV\nMoringa Oleifera (leaf) 800 mg **\n\n** Daily Value (DV) not established\n\nInactive Ingredients: Cellulose (Vegetable Capsule).\nDistributed by: successchemistry.com",
  "upc": "758475508742",
  "gtin": "758475508742",
  "weightOz": 3,
  "sizeInches": {
    "width": 2,
    "height": 3.5
  }
}